setup.py
My_own_serializer.egg-info/PKG-INFO
My_own_serializer.egg-info/SOURCES.txt
My_own_serializer.egg-info/dependency_links.txt
My_own_serializer.egg-info/requires.txt
My_own_serializer.egg-info/top_level.txt
serializer/__init__.py
serializer/constants.py
serializer/factory.py
serializer/myjson.py
serializer/myxml.py
serializer/utility_functions.py