Metadata-Version: 2.1
Name: My-own-serializer
Version: 0.0
Summary: Library for converting objects to xml and json format
Home-page: https://github.com/andrw04/Python-labs/tree/lab3
Author: Andrei Sivy
Author-email: sivyandrey2021@gmail.com
License: MIT
Platform: UNKNOWN
Classifier: Intended Audience :: Developers
Classifier: Programming Language :: Python :: 3.10
Classifier: Operating System :: OS Independent
